backend/__init__.py
backend/backend.py
canteens/__init__.py
canteens/cafenero.py
canteens/canteen.py
canteens/personalkantine.py
canteens/singh.py
canteens/studierendenwerk.py
frontend/__init__.py
frontend/frontend.py
omnbot-2017.5.dist-info/DESCRIPTION.rst
omnbot-2017.5.dist-info/METADATA
omnbot-2017.5.dist-info/RECORD
omnbot-2017.5.dist-info/WHEEL
omnbot-2017.5.dist-info/entry_points.txt
omnbot-2017.5.dist-info/metadata.json
omnbot-2017.5.dist-info/top_level.txt
omnomgram/__init__.py
omnomgram/tasks.py
stats/__init__.py
stats/tasks.py
