Metadata-Version: 2.0
Name: omnbot
Version: 2017.5
Summary: OmNomNom - A simple Telegram bot to get canteen information
Home-page: https://omnbot.io
Author: Max Rosin
Author-email: omnbot@hackrid.de
License: AGPL
Platform: UNKNOWN
Classifier: Programming Language :: Python :: 3
Requires-Python: >=3
Requires-Dist: beautifulsoup4
Requires-Dist: celery[redis]
Requires-Dist: dateparser
Requires-Dist: emoji
Requires-Dist: fake-useragent
Requires-Dist: flower
Requires-Dist: influxdb
Requires-Dist: parsedatetime
Requires-Dist: python-telegram-bot
Requires-Dist: redis
Requires-Dist: requests
